{
  "metadata" : {
    "identifier" : "https://nhattruyenz.com/truyen-tranh/yuru-fuwa-noka-no-moji-bake-skill",
    "title" : "Yuru Fuwa Noka No Moji Bake Skill",
    "subtitle" : null,
    "author" : null,
    "narrator" : null,
    "language" : "vi",
    "description" : null,
    "publisher" : "N/A",
    "subject" : null,
    "modified" : null,
    "published" : "2023-05-01",
    "duration" : 0,
    "abridged" : false,
    "conformsTo" : "https://readium.org/webpub-manifest/profiles/divina",
    "numberOfPages" : 6,
    "readingProgression" : "ttb",
    "belongsTo" : null,
    "presentation" : {
      "fit" : "width",
      "overflow" : "scrolled",
      "continuous" : true
    },
    "@type" : null,
    "schema:license" : null
  },
  "links" : [ {
    "rel" : "self",
    "href" : "https://raw.githubusercontent.com/thuvienonline40/book_storage_collection/main/comic_manifest.json",
    "type" : "application/divina+json"
  } ],
  "readingOrder" : [ {
    "href" : "https://raw.githubusercontent.com/tracuumasothue40/comic_storage_two1/main/IMAGE/IMAGE_e249c88b7aab7d1278d168b339352f98_e4e255ce2420e9f88881cf7c02d3ac88_8486069c81d5d66ac74fcef826645649.jpg",
    "type" : "image/jpeg",
    "bitrate" : 0,
    "duration" : 0,
    "title" : null,
    "properties" : null,
    "alternate" : [ {
      "href" : "https://img.abctruyen.xyz/uploads/19436/chuong-6/1.jpg",
      "type" : "image/jpeg",
      "bitrate" : 0,
      "duration" : 0,
      "title" : null,
      "properties" : null,
      "alternate" : null
    }, {
      "href" : "https://i2.wp.com/img.abctruyen.xyz/uploads/19436/chuong-6/1.jpg",
      "type" : "image/jpeg",
      "bitrate" : 0,
      "duration" : 0,
      "title" : null,
      "properties" : null,
      "alternate" : null
    } ]
  }, {
    "href" : "https://raw.githubusercontent.com/tracuumasothue40/comic_storage_two1/main/IMAGE/IMAGE_e249c88b7aab7d1278d168b339352f98_e4e255ce2420e9f88881cf7c02d3ac88_483d39dde72e5da367a2699fc809adf9.jpg",
    "type" : "image/jpeg",
    "bitrate" : 0,
    "duration" : 0,
    "title" : null,
    "properties" : null,
    "alternate" : [ {
      "href" : "https://img.abctruyen.xyz/uploads/19436/chuong-6/2.jpg",
      "type" : "image/jpeg",
      "bitrate" : 0,
      "duration" : 0,
      "title" : null,
      "properties" : null,
      "alternate" : null
    }, {
      "href" : "https://i2.wp.com/img.abctruyen.xyz/uploads/19436/chuong-6/2.jpg",
      "type" : "image/jpeg",
      "bitrate" : 0,
      "duration" : 0,
      "title" : null,
      "properties" : null,
      "alternate" : null
    } ]
  }, {
    "href" : "https://raw.githubusercontent.com/tracuumasothue40/comic_storage_two1/main/IMAGE/IMAGE_e249c88b7aab7d1278d168b339352f98_e4e255ce2420e9f88881cf7c02d3ac88_57a86262669bfa139c816570997905e5.jpg",
    "type" : "image/jpeg",
    "bitrate" : 0,
    "duration" : 0,
    "title" : null,
    "properties" : null,
    "alternate" : [ {
      "href" : "https://img.abctruyen.xyz/uploads/19436/chuong-6/3.jpg",
      "type" : "image/jpeg",
      "bitrate" : 0,
      "duration" : 0,
      "title" : null,
      "properties" : null,
      "alternate" : null
    }, {
      "href" : "https://i2.wp.com/img.abctruyen.xyz/uploads/19436/chuong-6/3.jpg",
      "type" : "image/jpeg",
      "bitrate" : 0,
      "duration" : 0,
      "title" : null,
      "properties" : null,
      "alternate" : null
    } ]
  }, {
    "href" : "https://raw.githubusercontent.com/tracuumasothue40/comic_storage_two1/main/IMAGE/IMAGE_e249c88b7aab7d1278d168b339352f98_e4e255ce2420e9f88881cf7c02d3ac88_b0a94783345590ffa36a10bf64167f66.jpg",
    "type" : "image/jpeg",
    "bitrate" : 0,
    "duration" : 0,
    "title" : null,
    "properties" : null,
    "alternate" : [ {
      "href" : "https://img.abctruyen.xyz/uploads/19436/chuong-6/4.jpg",
      "type" : "image/jpeg",
      "bitrate" : 0,
      "duration" : 0,
      "title" : null,
      "properties" : null,
      "alternate" : null
    }, {
      "href" : "https://i2.wp.com/img.abctruyen.xyz/uploads/19436/chuong-6/4.jpg",
      "type" : "image/jpeg",
      "bitrate" : 0,
      "duration" : 0,
      "title" : null,
      "properties" : null,
      "alternate" : null
    } ]
  }, {
    "href" : "https://raw.githubusercontent.com/tracuumasothue40/comic_storage_two1/main/IMAGE/IMAGE_e249c88b7aab7d1278d168b339352f98_e4e255ce2420e9f88881cf7c02d3ac88_c720a026a4c89a4f395dd2187b68a009.jpg",
    "type" : "image/jpeg",
    "bitrate" : 0,
    "duration" : 0,
    "title" : null,
    "properties" : null,
    "alternate" : [ {
      "href" : "https://img.abctruyen.xyz/uploads/19436/chuong-6/5.jpg",
      "type" : "image/jpeg",
      "bitrate" : 0,
      "duration" : 0,
      "title" : null,
      "properties" : null,
      "alternate" : null
    }, {
      "href" : "https://i2.wp.com/img.abctruyen.xyz/uploads/19436/chuong-6/5.jpg",
      "type" : "image/jpeg",
      "bitrate" : 0,
      "duration" : 0,
      "title" : null,
      "properties" : null,
      "alternate" : null
    } ]
  }, {
    "href" : "https://raw.githubusercontent.com/tracuumasothue40/comic_storage_two1/main/IMAGE/IMAGE_e249c88b7aab7d1278d168b339352f98_e4e255ce2420e9f88881cf7c02d3ac88_bcd003952c817fd546dd3947479d2895.jpg",
    "type" : "image/jpeg",
    "bitrate" : 0,
    "duration" : 0,
    "title" : null,
    "properties" : null,
    "alternate" : [ {
      "href" : "https://img.abctruyen.xyz/uploads/19436/chuong-6/6.jpg",
      "type" : "image/jpeg",
      "bitrate" : 0,
      "duration" : 0,
      "title" : null,
      "properties" : null,
      "alternate" : null
    }, {
      "href" : "https://i2.wp.com/img.abctruyen.xyz/uploads/19436/chuong-6/6.jpg",
      "type" : "image/jpeg",
      "bitrate" : 0,
      "duration" : 0,
      "title" : null,
      "properties" : null,
      "alternate" : null
    } ]
  }, {
    "href" : "https://raw.githubusercontent.com/tracuumasothue40/comic_storage_two1/main/IMAGE/IMAGE_e249c88b7aab7d1278d168b339352f98_e4e255ce2420e9f88881cf7c02d3ac88_841c4cd56cf043db5d545b9f8a0eb4ad.jpg",
    "type" : "image/jpeg",
    "bitrate" : 0,
    "duration" : 0,
    "title" : null,
    "properties" : null,
    "alternate" : [ {
      "href" : "https://img.abctruyen.xyz/uploads/19436/chuong-6/7.jpg",
      "type" : "image/jpeg",
      "bitrate" : 0,
      "duration" : 0,
      "title" : null,
      "properties" : null,
      "alternate" : null
    }, {
      "href" : "https://i2.wp.com/img.abctruyen.xyz/uploads/19436/chuong-6/7.jpg",
      "type" : "image/jpeg",
      "bitrate" : 0,
      "duration" : 0,
      "title" : null,
      "properties" : null,
      "alternate" : null
    } ]
  }, {
    "href" : "https://raw.githubusercontent.com/tracuumasothue40/comic_storage_two1/main/IMAGE/IMAGE_e249c88b7aab7d1278d168b339352f98_e4e255ce2420e9f88881cf7c02d3ac88_1e74dafed973906e34d1040b5e8e57be.jpg",
    "type" : "image/jpeg",
    "bitrate" : 0,
    "duration" : 0,
    "title" : null,
    "properties" : null,
    "alternate" : [ {
      "href" : "https://img.abctruyen.xyz/uploads/19436/chuong-6/8.jpg",
      "type" : "image/jpeg",
      "bitrate" : 0,
      "duration" : 0,
      "title" : null,
      "properties" : null,
      "alternate" : null
    }, {
      "href" : "https://i2.wp.com/img.abctruyen.xyz/uploads/19436/chuong-6/8.jpg",
      "type" : "image/jpeg",
      "bitrate" : 0,
      "duration" : 0,
      "title" : null,
      "properties" : null,
      "alternate" : null
    } ]
  }, {
    "href" : "https://raw.githubusercontent.com/tracuumasothue40/comic_storage_two1/main/IMAGE/IMAGE_e249c88b7aab7d1278d168b339352f98_e4e255ce2420e9f88881cf7c02d3ac88_159a003b6ac5f7cbc0760cd5f2af0968.jpg",
    "type" : "image/jpeg",
    "bitrate" : 0,
    "duration" : 0,
    "title" : null,
    "properties" : null,
    "alternate" : [ {
      "href" : "https://img.abctruyen.xyz/uploads/19436/chuong-6/9.jpg",
      "type" : "image/jpeg",
      "bitrate" : 0,
      "duration" : 0,
      "title" : null,
      "properties" : null,
      "alternate" : null
    }, {
      "href" : "https://i2.wp.com/img.abctruyen.xyz/uploads/19436/chuong-6/9.jpg",
      "type" : "image/jpeg",
      "bitrate" : 0,
      "duration" : 0,
      "title" : null,
      "properties" : null,
      "alternate" : null
    } ]
  }, {
    "href" : "https://raw.githubusercontent.com/tracuumasothue40/comic_storage_two1/main/IMAGE/IMAGE_e249c88b7aab7d1278d168b339352f98_e4e255ce2420e9f88881cf7c02d3ac88_baf840c2e38f0aea98d49b5a87f6b162.jpg",
    "type" : "image/jpeg",
    "bitrate" : 0,
    "duration" : 0,
    "title" : null,
    "properties" : null,
    "alternate" : [ {
      "href" : "https://img.abctruyen.xyz/uploads/19436/chuong-6/10.jpg",
      "type" : "image/jpeg",
      "bitrate" : 0,
      "duration" : 0,
      "title" : null,
      "properties" : null,
      "alternate" : null
    }, {
      "href" : "https://i2.wp.com/img.abctruyen.xyz/uploads/19436/chuong-6/10.jpg",
      "type" : "image/jpeg",
      "bitrate" : 0,
      "duration" : 0,
      "title" : null,
      "properties" : null,
      "alternate" : null
    } ]
  }, {
    "href" : "https://raw.githubusercontent.com/tracuumasothue40/comic_storage_two1/main/IMAGE/IMAGE_e249c88b7aab7d1278d168b339352f98_e4e255ce2420e9f88881cf7c02d3ac88_d6450d7d54972ac59bcb3cd2a48c57ec.jpg",
    "type" : "image/jpeg",
    "bitrate" : 0,
    "duration" : 0,
    "title" : null,
    "properties" : null,
    "alternate" : [ {
      "href" : "https://img.abctruyen.xyz/uploads/19436/chuong-6/11.jpg",
      "type" : "image/jpeg",
      "bitrate" : 0,
      "duration" : 0,
      "title" : null,
      "properties" : null,
      "alternate" : null
    }, {
      "href" : "https://i2.wp.com/img.abctruyen.xyz/uploads/19436/chuong-6/11.jpg",
      "type" : "image/jpeg",
      "bitrate" : 0,
      "duration" : 0,
      "title" : null,
      "properties" : null,
      "alternate" : null
    } ]
  }, {
    "href" : "https://raw.githubusercontent.com/tracuumasothue40/comic_storage_two1/main/IMAGE/IMAGE_e249c88b7aab7d1278d168b339352f98_e4e255ce2420e9f88881cf7c02d3ac88_8a65b88796735263e26185fb20465b9f.jpg",
    "type" : "image/jpeg",
    "bitrate" : 0,
    "duration" : 0,
    "title" : null,
    "properties" : null,
    "alternate" : [ {
      "href" : "https://img.abctruyen.xyz/uploads/19436/chuong-6/12.jpg",
      "type" : "image/jpeg",
      "bitrate" : 0,
      "duration" : 0,
      "title" : null,
      "properties" : null,
      "alternate" : null
    }, {
      "href" : "https://i2.wp.com/img.abctruyen.xyz/uploads/19436/chuong-6/12.jpg",
      "type" : "image/jpeg",
      "bitrate" : 0,
      "duration" : 0,
      "title" : null,
      "properties" : null,
      "alternate" : null
    } ]
  }, {
    "href" : "https://raw.githubusercontent.com/tracuumasothue40/comic_storage_two1/main/IMAGE/IMAGE_e249c88b7aab7d1278d168b339352f98_e4e255ce2420e9f88881cf7c02d3ac88_996f3e850600f0cb29c596e48e686d4e.jpg",
    "type" : "image/jpeg",
    "bitrate" : 0,
    "duration" : 0,
    "title" : null,
    "properties" : null,
    "alternate" : [ {
      "href" : "https://img.abctruyen.xyz/uploads/19436/chuong-6/13.jpg",
      "type" : "image/jpeg",
      "bitrate" : 0,
      "duration" : 0,
      "title" : null,
      "properties" : null,
      "alternate" : null
    }, {
      "href" : "https://i2.wp.com/img.abctruyen.xyz/uploads/19436/chuong-6/13.jpg",
      "type" : "image/jpeg",
      "bitrate" : 0,
      "duration" : 0,
      "title" : null,
      "properties" : null,
      "alternate" : null
    } ]
  }, {
    "href" : "https://raw.githubusercontent.com/tracuumasothue40/comic_storage_two1/main/IMAGE/IMAGE_e249c88b7aab7d1278d168b339352f98_e4e255ce2420e9f88881cf7c02d3ac88_ebf8d12e432604fd652daab666f9d5f5.jpg",
    "type" : "image/jpeg",
    "bitrate" : 0,
    "duration" : 0,
    "title" : null,
    "properties" : null,
    "alternate" : [ {
      "href" : "https://img.abctruyen.xyz/uploads/19436/chuong-6/14.jpg",
      "type" : "image/jpeg",
      "bitrate" : 0,
      "duration" : 0,
      "title" : null,
      "properties" : null,
      "alternate" : null
    }, {
      "href" : "https://i2.wp.com/img.abctruyen.xyz/uploads/19436/chuong-6/14.jpg",
      "type" : "image/jpeg",
      "bitrate" : 0,
      "duration" : 0,
      "title" : null,
      "properties" : null,
      "alternate" : null
    } ]
  }, {
    "href" : "https://raw.githubusercontent.com/tracuumasothue40/comic_storage_two1/main/IMAGE/IMAGE_e249c88b7aab7d1278d168b339352f98_e4e255ce2420e9f88881cf7c02d3ac88_23f6247dfa460d3a3d84b0bfdfe1a777.jpg",
    "type" : "image/jpeg",
    "bitrate" : 0,
    "duration" : 0,
    "title" : null,
    "properties" : null,
    "alternate" : [ {
      "href" : "https://img.abctruyen.xyz/uploads/19436/chuong-6/15.jpg",
      "type" : "image/jpeg",
      "bitrate" : 0,
      "duration" : 0,
      "title" : null,
      "properties" : null,
      "alternate" : null
    }, {
      "href" : "https://i2.wp.com/img.abctruyen.xyz/uploads/19436/chuong-6/15.jpg",
      "type" : "image/jpeg",
      "bitrate" : 0,
      "duration" : 0,
      "title" : null,
      "properties" : null,
      "alternate" : null
    } ]
  }, {
    "href" : "https://raw.githubusercontent.com/tracuumasothue40/comic_storage_two1/main/IMAGE/IMAGE_e249c88b7aab7d1278d168b339352f98_e4e255ce2420e9f88881cf7c02d3ac88_7c958026254c8da4b8bbc8b46a7fb2d7.jpg",
    "type" : "image/jpeg",
    "bitrate" : 0,
    "duration" : 0,
    "title" : null,
    "properties" : null,
    "alternate" : [ {
      "href" : "https://img.abctruyen.xyz/uploads/19436/chuong-6/16.jpg",
      "type" : "image/jpeg",
      "bitrate" : 0,
      "duration" : 0,
      "title" : null,
      "properties" : null,
      "alternate" : null
    }, {
      "href" : "https://i2.wp.com/img.abctruyen.xyz/uploads/19436/chuong-6/16.jpg",
      "type" : "image/jpeg",
      "bitrate" : 0,
      "duration" : 0,
      "title" : null,
      "properties" : null,
      "alternate" : null
    } ]
  }, {
    "href" : "https://raw.githubusercontent.com/tracuumasothue40/comic_storage_two1/main/IMAGE/IMAGE_e249c88b7aab7d1278d168b339352f98_e4e255ce2420e9f88881cf7c02d3ac88_387774ddc107baee8f1324070323ef89.jpg",
    "type" : "image/jpeg",
    "bitrate" : 0,
    "duration" : 0,
    "title" : null,
    "properties" : null,
    "alternate" : [ {
      "href" : "https://img.abctruyen.xyz/uploads/19436/chuong-6/17.jpg",
      "type" : "image/jpeg",
      "bitrate" : 0,
      "duration" : 0,
      "title" : null,
      "properties" : null,
      "alternate" : null
    }, {
      "href" : "https://i2.wp.com/img.abctruyen.xyz/uploads/19436/chuong-6/17.jpg",
      "type" : "image/jpeg",
      "bitrate" : 0,
      "duration" : 0,
      "title" : null,
      "properties" : null,
      "alternate" : null
    } ]
  }, {
    "href" : "https://raw.githubusercontent.com/tracuumasothue40/comic_storage_two1/main/IMAGE/IMAGE_e249c88b7aab7d1278d168b339352f98_e4e255ce2420e9f88881cf7c02d3ac88_d14492b5fe72dbb8130e46d8fec0626a.jpg",
    "type" : "image/jpeg",
    "bitrate" : 0,
    "duration" : 0,
    "title" : null,
    "properties" : null,
    "alternate" : [ {
      "href" : "https://img.abctruyen.xyz/uploads/19436/chuong-6/18.jpg",
      "type" : "image/jpeg",
      "bitrate" : 0,
      "duration" : 0,
      "title" : null,
      "properties" : null,
      "alternate" : null
    }, {
      "href" : "https://i2.wp.com/img.abctruyen.xyz/uploads/19436/chuong-6/18.jpg",
      "type" : "image/jpeg",
      "bitrate" : 0,
      "duration" : 0,
      "title" : null,
      "properties" : null,
      "alternate" : null
    } ]
  }, {
    "href" : "https://raw.githubusercontent.com/tracuumasothue40/comic_storage_two1/main/IMAGE/IMAGE_e249c88b7aab7d1278d168b339352f98_e4e255ce2420e9f88881cf7c02d3ac88_ed9bcb1fc8ede6d66f2f2f5e923cab3d.jpg",
    "type" : "image/jpeg",
    "bitrate" : 0,
    "duration" : 0,
    "title" : null,
    "properties" : null,
    "alternate" : [ {
      "href" : "https://img.abctruyen.xyz/uploads/19436/chuong-6/19.jpg",
      "type" : "image/jpeg",
      "bitrate" : 0,
      "duration" : 0,
      "title" : null,
      "properties" : null,
      "alternate" : null
    }, {
      "href" : "https://i2.wp.com/img.abctruyen.xyz/uploads/19436/chuong-6/19.jpg",
      "type" : "image/jpeg",
      "bitrate" : 0,
      "duration" : 0,
      "title" : null,
      "properties" : null,
      "alternate" : null
    } ]
  }, {
    "href" : "https://raw.githubusercontent.com/tracuumasothue40/comic_storage_two1/main/IMAGE/IMAGE_e249c88b7aab7d1278d168b339352f98_e4e255ce2420e9f88881cf7c02d3ac88_18d3239ebd41f84f30ce35440ab31e13.jpg",
    "type" : "image/jpeg",
    "bitrate" : 0,
    "duration" : 0,
    "title" : null,
    "properties" : null,
    "alternate" : [ {
      "href" : "https://img.abctruyen.xyz/uploads/19436/chuong-6/20.jpg",
      "type" : "image/jpeg",
      "bitrate" : 0,
      "duration" : 0,
      "title" : null,
      "properties" : null,
      "alternate" : null
    }, {
      "href" : "https://i2.wp.com/img.abctruyen.xyz/uploads/19436/chuong-6/20.jpg",
      "type" : "image/jpeg",
      "bitrate" : 0,
      "duration" : 0,
      "title" : null,
      "properties" : null,
      "alternate" : null
    } ]
  }, {
    "href" : "https://raw.githubusercontent.com/tracuumasothue40/comic_storage_two1/main/IMAGE/IMAGE_e249c88b7aab7d1278d168b339352f98_e4e255ce2420e9f88881cf7c02d3ac88_fa5985a216dec21a7066e910642e7f7d.jpg",
    "type" : "image/jpeg",
    "bitrate" : 0,
    "duration" : 0,
    "title" : null,
    "properties" : null,
    "alternate" : [ {
      "href" : "https://img.abctruyen.xyz/uploads/19436/chuong-6/21.jpg",
      "type" : "image/jpeg",
      "bitrate" : 0,
      "duration" : 0,
      "title" : null,
      "properties" : null,
      "alternate" : null
    }, {
      "href" : "https://i2.wp.com/img.abctruyen.xyz/uploads/19436/chuong-6/21.jpg",
      "type" : "image/jpeg",
      "bitrate" : 0,
      "duration" : 0,
      "title" : null,
      "properties" : null,
      "alternate" : null
    } ]
  }, {
    "href" : "https://raw.githubusercontent.com/tracuumasothue40/comic_storage_two1/main/IMAGE/IMAGE_e249c88b7aab7d1278d168b339352f98_e4e255ce2420e9f88881cf7c02d3ac88_d303a2d02bf9e42ff03a6aa04f708d99.jpg",
    "type" : "image/jpeg",
    "bitrate" : 0,
    "duration" : 0,
    "title" : null,
    "properties" : null,
    "alternate" : [ {
      "href" : "https://img.abctruyen.xyz/uploads/19436/chuong-6/22.jpg",
      "type" : "image/jpeg",
      "bitrate" : 0,
      "duration" : 0,
      "title" : null,
      "properties" : null,
      "alternate" : null
    }, {
      "href" : "https://i2.wp.com/img.abctruyen.xyz/uploads/19436/chuong-6/22.jpg",
      "type" : "image/jpeg",
      "bitrate" : 0,
      "duration" : 0,
      "title" : null,
      "properties" : null,
      "alternate" : null
    } ]
  }, {
    "href" : "https://raw.githubusercontent.com/tracuumasothue40/comic_storage_two1/main/IMAGE/IMAGE_e249c88b7aab7d1278d168b339352f98_e4e255ce2420e9f88881cf7c02d3ac88_69606cb85fe5de6d67b63e9f25926883.jpg",
    "type" : "image/jpeg",
    "bitrate" : 0,
    "duration" : 0,
    "title" : null,
    "properties" : null,
    "alternate" : [ {
      "href" : "https://img.abctruyen.xyz/uploads/19436/chuong-6/23.jpg",
      "type" : "image/jpeg",
      "bitrate" : 0,
      "duration" : 0,
      "title" : null,
      "properties" : null,
      "alternate" : null
    }, {
      "href" : "https://i2.wp.com/img.abctruyen.xyz/uploads/19436/chuong-6/23.jpg",
      "type" : "image/jpeg",
      "bitrate" : 0,
      "duration" : 0,
      "title" : null,
      "properties" : null,
      "alternate" : null
    } ]
  }, {
    "href" : "https://raw.githubusercontent.com/tracuumasothue40/comic_storage_two1/main/IMAGE/IMAGE_e249c88b7aab7d1278d168b339352f98_e4e255ce2420e9f88881cf7c02d3ac88_574e07a1d13cc4ab92cc646a6c70a656.jpg",
    "type" : "image/jpeg",
    "bitrate" : 0,
    "duration" : 0,
    "title" : null,
    "properties" : null,
    "alternate" : [ {
      "href" : "https://img.abctruyen.xyz/uploads/19436/chuong-6/24.jpg",
      "type" : "image/jpeg",
      "bitrate" : 0,
      "duration" : 0,
      "title" : null,
      "properties" : null,
      "alternate" : null
    }, {
      "href" : "https://i2.wp.com/img.abctruyen.xyz/uploads/19436/chuong-6/24.jpg",
      "type" : "image/jpeg",
      "bitrate" : 0,
      "duration" : 0,
      "title" : null,
      "properties" : null,
      "alternate" : null
    } ]
  }, {
    "href" : "https://raw.githubusercontent.com/tracuumasothue40/comic_storage_two1/main/IMAGE/IMAGE_e249c88b7aab7d1278d168b339352f98_e4e255ce2420e9f88881cf7c02d3ac88_2aebdbadf3c0fcb847e5ac5be5a5b573.jpg",
    "type" : "image/jpeg",
    "bitrate" : 0,
    "duration" : 0,
    "title" : null,
    "properties" : null,
    "alternate" : [ {
      "href" : "https://img.abctruyen.xyz/uploads/19436/chuong-6/25.jpg",
      "type" : "image/jpeg",
      "bitrate" : 0,
      "duration" : 0,
      "title" : null,
      "properties" : null,
      "alternate" : null
    }, {
      "href" : "https://i2.wp.com/img.abctruyen.xyz/uploads/19436/chuong-6/25.jpg",
      "type" : "image/jpeg",
      "bitrate" : 0,
      "duration" : 0,
      "title" : null,
      "properties" : null,
      "alternate" : null
    } ]
  }, {
    "href" : "https://raw.githubusercontent.com/tracuumasothue40/comic_storage_two1/main/IMAGE/IMAGE_e249c88b7aab7d1278d168b339352f98_e4e255ce2420e9f88881cf7c02d3ac88_8d5dfe73d077f9284050d58f54af39a1.jpg",
    "type" : "image/jpeg",
    "bitrate" : 0,
    "duration" : 0,
    "title" : null,
    "properties" : null,
    "alternate" : [ {
      "href" : "https://img.abctruyen.xyz/uploads/19436/chuong-6/26.jpg",
      "type" : "image/jpeg",
      "bitrate" : 0,
      "duration" : 0,
      "title" : null,
      "properties" : null,
      "alternate" : null
    }, {
      "href" : "https://i2.wp.com/img.abctruyen.xyz/uploads/19436/chuong-6/26.jpg",
      "type" : "image/jpeg",
      "bitrate" : 0,
      "duration" : 0,
      "title" : null,
      "properties" : null,
      "alternate" : null
    } ]
  }, {
    "href" : "https://raw.githubusercontent.com/tracuumasothue40/comic_storage_two1/main/IMAGE/IMAGE_e249c88b7aab7d1278d168b339352f98_e4e255ce2420e9f88881cf7c02d3ac88_95ba6e51acbaf1dc1ddbcbd468e1a7d8.jpg",
    "type" : "image/jpeg",
    "bitrate" : 0,
    "duration" : 0,
    "title" : null,
    "properties" : null,
    "alternate" : [ {
      "href" : "https://img.abctruyen.xyz/uploads/19436/chuong-6/27.jpg",
      "type" : "image/jpeg",
      "bitrate" : 0,
      "duration" : 0,
      "title" : null,
      "properties" : null,
      "alternate" : null
    }, {
      "href" : "https://i2.wp.com/img.abctruyen.xyz/uploads/19436/chuong-6/27.jpg",
      "type" : "image/jpeg",
      "bitrate" : 0,
      "duration" : 0,
      "title" : null,
      "properties" : null,
      "alternate" : null
    } ]
  }, {
    "href" : "https://raw.githubusercontent.com/tracuumasothue40/comic_storage_two1/main/IMAGE/IMAGE_e249c88b7aab7d1278d168b339352f98_e4e255ce2420e9f88881cf7c02d3ac88_fba6e3f3b61ddf9c7402d71ef6c747e4.jpg",
    "type" : "image/jpeg",
    "bitrate" : 0,
    "duration" : 0,
    "title" : null,
    "properties" : null,
    "alternate" : [ {
      "href" : "https://img.abctruyen.xyz/uploads/19436/chuong-6/28.jpg",
      "type" : "image/jpeg",
      "bitrate" : 0,
      "duration" : 0,
      "title" : null,
      "properties" : null,
      "alternate" : null
    }, {
      "href" : "https://i2.wp.com/img.abctruyen.xyz/uploads/19436/chuong-6/28.jpg",
      "type" : "image/jpeg",
      "bitrate" : 0,
      "duration" : 0,
      "title" : null,
      "properties" : null,
      "alternate" : null
    } ]
  }, {
    "href" : "https://raw.githubusercontent.com/tracuumasothue40/comic_storage_two1/main/IMAGE/IMAGE_e249c88b7aab7d1278d168b339352f98_e4e255ce2420e9f88881cf7c02d3ac88_7e8aa5f34f1a578baab24761f601d5ed.jpg",
    "type" : "image/jpeg",
    "bitrate" : 0,
    "duration" : 0,
    "title" : null,
    "properties" : null,
    "alternate" : [ {
      "href" : "https://img.abctruyen.xyz/uploads/19436/chuong-6/29.jpg",
      "type" : "image/jpeg",
      "bitrate" : 0,
      "duration" : 0,
      "title" : null,
      "properties" : null,
      "alternate" : null
    }, {
      "href" : "https://i2.wp.com/img.abctruyen.xyz/uploads/19436/chuong-6/29.jpg",
      "type" : "image/jpeg",
      "bitrate" : 0,
      "duration" : 0,
      "title" : null,
      "properties" : null,
      "alternate" : null
    } ]
  }, {
    "href" : "https://raw.githubusercontent.com/tracuumasothue40/comic_storage_two1/main/IMAGE/IMAGE_e249c88b7aab7d1278d168b339352f98_e4e255ce2420e9f88881cf7c02d3ac88_d174ee20e07f2161f4425cacb12f0833.jpg",
    "type" : "image/jpeg",
    "bitrate" : 0,
    "duration" : 0,
    "title" : null,
    "properties" : null,
    "alternate" : [ {
      "href" : "https://img.abctruyen.xyz/uploads/19436/chuong-6/30.jpg",
      "type" : "image/jpeg",
      "bitrate" : 0,
      "duration" : 0,
      "title" : null,
      "properties" : null,
      "alternate" : null
    }, {
      "href" : "https://i2.wp.com/img.abctruyen.xyz/uploads/19436/chuong-6/30.jpg",
      "type" : "image/jpeg",
      "bitrate" : 0,
      "duration" : 0,
      "title" : null,
      "properties" : null,
      "alternate" : null
    } ]
  }, {
    "href" : "https://raw.githubusercontent.com/tracuumasothue40/comic_storage_two1/main/IMAGE/IMAGE_e249c88b7aab7d1278d168b339352f98_e4e255ce2420e9f88881cf7c02d3ac88_fa16a3f741bce517c8869ea06deb5b73.jpg",
    "type" : "image/jpeg",
    "bitrate" : 0,
    "duration" : 0,
    "title" : null,
    "properties" : null,
    "alternate" : [ {
      "href" : "https://img.abctruyen.xyz/uploads/19436/chuong-6/31.jpg",
      "type" : "image/jpeg",
      "bitrate" : 0,
      "duration" : 0,
      "title" : null,
      "properties" : null,
      "alternate" : null
    }, {
      "href" : "https://i2.wp.com/img.abctruyen.xyz/uploads/19436/chuong-6/31.jpg",
      "type" : "image/jpeg",
      "bitrate" : 0,
      "duration" : 0,
      "title" : null,
      "properties" : null,
      "alternate" : null
    } ]
  }, {
    "href" : "https://raw.githubusercontent.com/tracuumasothue40/comic_storage_two1/main/IMAGE/IMAGE_e249c88b7aab7d1278d168b339352f98_e4e255ce2420e9f88881cf7c02d3ac88_ede51602ebe0e05b9d378801237d4513.jpg",
    "type" : "image/jpeg",
    "bitrate" : 0,
    "duration" : 0,
    "title" : null,
    "properties" : null,
    "alternate" : [ {
      "href" : "https://img.abctruyen.xyz/uploads/19436/chuong-6/32.jpg",
      "type" : "image/jpeg",
      "bitrate" : 0,
      "duration" : 0,
      "title" : null,
      "properties" : null,
      "alternate" : null
    }, {
      "href" : "https://i2.wp.com/img.abctruyen.xyz/uploads/19436/chuong-6/32.jpg",
      "type" : "image/jpeg",
      "bitrate" : 0,
      "duration" : 0,
      "title" : null,
      "properties" : null,
      "alternate" : null
    } ]
  }, {
    "href" : "https://raw.githubusercontent.com/tracuumasothue40/comic_storage_two1/main/IMAGE/IMAGE_e249c88b7aab7d1278d168b339352f98_e4e255ce2420e9f88881cf7c02d3ac88_043c3ea32dc296f965e4c7ee183bebe4.jpg",
    "type" : "image/jpeg",
    "bitrate" : 0,
    "duration" : 0,
    "title" : null,
    "properties" : null,
    "alternate" : [ {
      "href" : "https://img.abctruyen.xyz/uploads/19436/chuong-6/33.jpg",
      "type" : "image/jpeg",
      "bitrate" : 0,
      "duration" : 0,
      "title" : null,
      "properties" : null,
      "alternate" : null
    }, {
      "href" : "https://i2.wp.com/img.abctruyen.xyz/uploads/19436/chuong-6/33.jpg",
      "type" : "image/jpeg",
      "bitrate" : 0,
      "duration" : 0,
      "title" : null,
      "properties" : null,
      "alternate" : null
    } ]
  }, {
    "href" : "https://raw.githubusercontent.com/tracuumasothue40/comic_storage_two1/main/IMAGE/IMAGE_e249c88b7aab7d1278d168b339352f98_e4e255ce2420e9f88881cf7c02d3ac88_f7a2bede4ea54baeaa18b2d04c904534.jpg",
    "type" : "image/jpeg",
    "bitrate" : 0,
    "duration" : 0,
    "title" : null,
    "properties" : null,
    "alternate" : [ {
      "href" : "https://img.abctruyen.xyz/uploads/19436/chuong-6/34.jpg",
      "type" : "image/jpeg",
      "bitrate" : 0,
      "duration" : 0,
      "title" : null,
      "properties" : null,
      "alternate" : null
    }, {
      "href" : "https://i2.wp.com/img.abctruyen.xyz/uploads/19436/chuong-6/34.jpg",
      "type" : "image/jpeg",
      "bitrate" : 0,
      "duration" : 0,
      "title" : null,
      "properties" : null,
      "alternate" : null
    } ]
  }, {
    "href" : "https://raw.githubusercontent.com/tracuumasothue40/comic_storage_two1/main/IMAGE/IMAGE_e249c88b7aab7d1278d168b339352f98_e4e255ce2420e9f88881cf7c02d3ac88_c2b104fb866db31d198ca696537293c1.jpg",
    "type" : "image/jpeg",
    "bitrate" : 0,
    "duration" : 0,
    "title" : null,
    "properties" : null,
    "alternate" : [ {
      "href" : "https://img.abctruyen.xyz/uploads/19436/chuong-6/35.jpg",
      "type" : "image/jpeg",
      "bitrate" : 0,
      "duration" : 0,
      "title" : null,
      "properties" : null,
      "alternate" : null
    }, {
      "href" : "https://i2.wp.com/img.abctruyen.xyz/uploads/19436/chuong-6/35.jpg",
      "type" : "image/jpeg",
      "bitrate" : 0,
      "duration" : 0,
      "title" : null,
      "properties" : null,
      "alternate" : null
    } ]
  }, {
    "href" : "https://raw.githubusercontent.com/tracuumasothue40/comic_storage_two1/main/IMAGE/IMAGE_e249c88b7aab7d1278d168b339352f98_e4e255ce2420e9f88881cf7c02d3ac88_e631fc69a48e04aa9e52038fa0e0f99b.jpg",
    "type" : "image/jpeg",
    "bitrate" : 0,
    "duration" : 0,
    "title" : null,
    "properties" : null,
    "alternate" : [ {
      "href" : "https://img.abctruyen.xyz/uploads/19436/chuong-6/36.jpg",
      "type" : "image/jpeg",
      "bitrate" : 0,
      "duration" : 0,
      "title" : null,
      "properties" : null,
      "alternate" : null
    }, {
      "href" : "https://i2.wp.com/img.abctruyen.xyz/uploads/19436/chuong-6/36.jpg",
      "type" : "image/jpeg",
      "bitrate" : 0,
      "duration" : 0,
      "title" : null,
      "properties" : null,
      "alternate" : null
    } ]
  }, {
    "href" : "https://raw.githubusercontent.com/tracuumasothue40/comic_storage_two1/main/IMAGE/IMAGE_e249c88b7aab7d1278d168b339352f98_e4e255ce2420e9f88881cf7c02d3ac88_44cbdb523ca81c811a74f906991687d1.jpg",
    "type" : "image/jpeg",
    "bitrate" : 0,
    "duration" : 0,
    "title" : null,
    "properties" : null,
    "alternate" : [ {
      "href" : "https://img.abctruyen.xyz/uploads/19436/chuong-6/37.jpg",
      "type" : "image/jpeg",
      "bitrate" : 0,
      "duration" : 0,
      "title" : null,
      "properties" : null,
      "alternate" : null
    }, {
      "href" : "https://i2.wp.com/img.abctruyen.xyz/uploads/19436/chuong-6/37.jpg",
      "type" : "image/jpeg",
      "bitrate" : 0,
      "duration" : 0,
      "title" : null,
      "properties" : null,
      "alternate" : null
    } ]
  }, {
    "href" : "https://raw.githubusercontent.com/tracuumasothue40/comic_storage_two1/main/IMAGE/IMAGE_e249c88b7aab7d1278d168b339352f98_e4e255ce2420e9f88881cf7c02d3ac88_c47c9f49f652fa12302498e5e8095a96.jpg",
    "type" : "image/jpeg",
    "bitrate" : 0,
    "duration" : 0,
    "title" : null,
    "properties" : null,
    "alternate" : [ {
      "href" : "https://img.abctruyen.xyz/uploads/19436/chuong-6/38.jpg",
      "type" : "image/jpeg",
      "bitrate" : 0,
      "duration" : 0,
      "title" : null,
      "properties" : null,
      "alternate" : null
    }, {
      "href" : "https://i2.wp.com/img.abctruyen.xyz/uploads/19436/chuong-6/38.jpg",
      "type" : "image/jpeg",
      "bitrate" : 0,
      "duration" : 0,
      "title" : null,
      "properties" : null,
      "alternate" : null
    } ]
  }, {
    "href" : "https://raw.githubusercontent.com/tracuumasothue40/comic_storage_two1/main/IMAGE/IMAGE_e249c88b7aab7d1278d168b339352f98_e4e255ce2420e9f88881cf7c02d3ac88_e535196e6b91c79c9661e548f4eabb1d.jpg",
    "type" : "image/jpeg",
    "bitrate" : 0,
    "duration" : 0,
    "title" : null,
    "properties" : null,
    "alternate" : [ {
      "href" : "https://img.abctruyen.xyz/uploads/19436/chuong-6/39.jpg",
      "type" : "image/jpeg",
      "bitrate" : 0,
      "duration" : 0,
      "title" : null,
      "properties" : null,
      "alternate" : null
    }, {
      "href" : "https://i2.wp.com/img.abctruyen.xyz/uploads/19436/chuong-6/39.jpg",
      "type" : "image/jpeg",
      "bitrate" : 0,
      "duration" : 0,
      "title" : null,
      "properties" : null,
      "alternate" : null
    } ]
  }, {
    "href" : "https://raw.githubusercontent.com/tracuumasothue40/comic_storage_two1/main/IMAGE/IMAGE_e249c88b7aab7d1278d168b339352f98_e4e255ce2420e9f88881cf7c02d3ac88_c0d10c4b21fc6334add19fada635625c.jpg",
    "type" : "image/jpeg",
    "bitrate" : 0,
    "duration" : 0,
    "title" : null,
    "properties" : null,
    "alternate" : [ {
      "href" : "https://img.abctruyen.xyz/uploads/19436/chuong-6/40.jpg",
      "type" : "image/jpeg",
      "bitrate" : 0,
      "duration" : 0,
      "title" : null,
      "properties" : null,
      "alternate" : null
    }, {
      "href" : "https://i2.wp.com/img.abctruyen.xyz/uploads/19436/chuong-6/40.jpg",
      "type" : "image/jpeg",
      "bitrate" : 0,
      "duration" : 0,
      "title" : null,
      "properties" : null,
      "alternate" : null
    } ]
  }, {
    "href" : "https://raw.githubusercontent.com/tracuumasothue40/comic_storage_two1/main/IMAGE/IMAGE_e249c88b7aab7d1278d168b339352f98_e4e255ce2420e9f88881cf7c02d3ac88_b2acae7d80f69d11a2857d495bc5cbfe.jpg",
    "type" : "image/jpeg",
    "bitrate" : 0,
    "duration" : 0,
    "title" : null,
    "properties" : null,
    "alternate" : [ {
      "href" : "https://img.abctruyen.xyz/uploads/19436/chuong-6/41.jpg",
      "type" : "image/jpeg",
      "bitrate" : 0,
      "duration" : 0,
      "title" : null,
      "properties" : null,
      "alternate" : null
    }, {
      "href" : "https://i2.wp.com/img.abctruyen.xyz/uploads/19436/chuong-6/41.jpg",
      "type" : "image/jpeg",
      "bitrate" : 0,
      "duration" : 0,
      "title" : null,
      "properties" : null,
      "alternate" : null
    } ]
  }, {
    "href" : "https://raw.githubusercontent.com/tracuumasothue40/comic_storage_two1/main/IMAGE/IMAGE_e249c88b7aab7d1278d168b339352f98_e4e255ce2420e9f88881cf7c02d3ac88_34bb4ceb2862303ceb1717dcaaf13b70.jpg",
    "type" : "image/jpeg",
    "bitrate" : 0,
    "duration" : 0,
    "title" : null,
    "properties" : null,
    "alternate" : [ {
      "href" : "https://img.abctruyen.xyz/uploads/19436/chuong-6/42.jpg",
      "type" : "image/jpeg",
      "bitrate" : 0,
      "duration" : 0,
      "title" : null,
      "properties" : null,
      "alternate" : null
    }, {
      "href" : "https://i2.wp.com/img.abctruyen.xyz/uploads/19436/chuong-6/42.jpg",
      "type" : "image/jpeg",
      "bitrate" : 0,
      "duration" : 0,
      "title" : null,
      "properties" : null,
      "alternate" : null
    } ]
  }, {
    "href" : "https://raw.githubusercontent.com/tracuumasothue40/comic_storage_two1/main/IMAGE/IMAGE_e249c88b7aab7d1278d168b339352f98_e4e255ce2420e9f88881cf7c02d3ac88_e4cdf49396f02c94cf06f3bd3db42bbe.jpg",
    "type" : "image/jpeg",
    "bitrate" : 0,
    "duration" : 0,
    "title" : null,
    "properties" : null,
    "alternate" : [ {
      "href" : "https://img.abctruyen.xyz/uploads/19436/chuong-6/43.jpg",
      "type" : "image/jpeg",
      "bitrate" : 0,
      "duration" : 0,
      "title" : null,
      "properties" : null,
      "alternate" : null
    }, {
      "href" : "https://i2.wp.com/img.abctruyen.xyz/uploads/19436/chuong-6/43.jpg",
      "type" : "image/jpeg",
      "bitrate" : 0,
      "duration" : 0,
      "title" : null,
      "properties" : null,
      "alternate" : null
    } ]
  }, {
    "href" : "https://raw.githubusercontent.com/tracuumasothue40/comic_storage_two1/main/IMAGE/IMAGE_e249c88b7aab7d1278d168b339352f98_e4e255ce2420e9f88881cf7c02d3ac88_9ef0aff1658739c3efb2bba2e66f5bc7.jpg",
    "type" : "image/jpeg",
    "bitrate" : 0,
    "duration" : 0,
    "title" : null,
    "properties" : null,
    "alternate" : [ {
      "href" : "https://img.abctruyen.xyz/uploads/19436/chuong-6/44.jpg",
      "type" : "image/jpeg",
      "bitrate" : 0,
      "duration" : 0,
      "title" : null,
      "properties" : null,
      "alternate" : null
    }, {
      "href" : "https://i2.wp.com/img.abctruyen.xyz/uploads/19436/chuong-6/44.jpg",
      "type" : "image/jpeg",
      "bitrate" : 0,
      "duration" : 0,
      "title" : null,
      "properties" : null,
      "alternate" : null
    } ]
  }, {
    "href" : "https://raw.githubusercontent.com/tracuumasothue40/comic_storage_two1/main/IMAGE/IMAGE_e249c88b7aab7d1278d168b339352f98_e4e255ce2420e9f88881cf7c02d3ac88_2629fc09557bc72af931800cbe68abc0.jpg",
    "type" : "image/jpeg",
    "bitrate" : 0,
    "duration" : 0,
    "title" : null,
    "properties" : null,
    "alternate" : [ {
      "href" : "https://img.abctruyen.xyz/uploads/19436/chuong-6/45.jpg",
      "type" : "image/jpeg",
      "bitrate" : 0,
      "duration" : 0,
      "title" : null,
      "properties" : null,
      "alternate" : null
    }, {
      "href" : "https://i2.wp.com/img.abctruyen.xyz/uploads/19436/chuong-6/45.jpg",
      "type" : "image/jpeg",
      "bitrate" : 0,
      "duration" : 0,
      "title" : null,
      "properties" : null,
      "alternate" : null
    } ]
  }, {
    "href" : "https://raw.githubusercontent.com/tracuumasothue40/comic_storage_two1/main/IMAGE/IMAGE_e249c88b7aab7d1278d168b339352f98_e4e255ce2420e9f88881cf7c02d3ac88_e88e65206370357a950def3e281bfb61.jpg",
    "type" : "image/jpeg",
    "bitrate" : 0,
    "duration" : 0,
    "title" : null,
    "properties" : null,
    "alternate" : [ {
      "href" : "https://img.abctruyen.xyz/uploads/19436/chuong-6/46.jpg",
      "type" : "image/jpeg",
      "bitrate" : 0,
      "duration" : 0,
      "title" : null,
      "properties" : null,
      "alternate" : null
    }, {
      "href" : "https://i2.wp.com/img.abctruyen.xyz/uploads/19436/chuong-6/46.jpg",
      "type" : "image/jpeg",
      "bitrate" : 0,
      "duration" : 0,
      "title" : null,
      "properties" : null,
      "alternate" : null
    } ]
  }, {
    "href" : "https://raw.githubusercontent.com/tracuumasothue40/comic_storage_two1/main/IMAGE/IMAGE_e249c88b7aab7d1278d168b339352f98_e4e255ce2420e9f88881cf7c02d3ac88_a968a92b65b8ec15c8ff56312143f7c8.jpg",
    "type" : "image/jpeg",
    "bitrate" : 0,
    "duration" : 0,
    "title" : null,
    "properties" : null,
    "alternate" : [ {
      "href" : "https://img.abctruyen.xyz/uploads/19436/chuong-6/47.jpg",
      "type" : "image/jpeg",
      "bitrate" : 0,
      "duration" : 0,
      "title" : null,
      "properties" : null,
      "alternate" : null
    }, {
      "href" : "https://i2.wp.com/img.abctruyen.xyz/uploads/19436/chuong-6/47.jpg",
      "type" : "image/jpeg",
      "bitrate" : 0,
      "duration" : 0,
      "title" : null,
      "properties" : null,
      "alternate" : null
    } ]
  }, {
    "href" : "https://raw.githubusercontent.com/tracuumasothue40/comic_storage_two1/main/IMAGE/IMAGE_e249c88b7aab7d1278d168b339352f98_e4e255ce2420e9f88881cf7c02d3ac88_c8996578dad35755968d406e12658d11.jpg",
    "type" : "image/jpeg",
    "bitrate" : 0,
    "duration" : 0,
    "title" : null,
    "properties" : null,
    "alternate" : [ {
      "href" : "https://img.abctruyen.xyz/uploads/19436/chuong-6/48.jpg",
      "type" : "image/jpeg",
      "bitrate" : 0,
      "duration" : 0,
      "title" : null,
      "properties" : null,
      "alternate" : null
    }, {
      "href" : "https://i2.wp.com/img.abctruyen.xyz/uploads/19436/chuong-6/48.jpg",
      "type" : "image/jpeg",
      "bitrate" : 0,
      "duration" : 0,
      "title" : null,
      "properties" : null,
      "alternate" : null
    } ]
  }, {
    "href" : "https://raw.githubusercontent.com/tracuumasothue40/comic_storage_two1/main/IMAGE/IMAGE_e249c88b7aab7d1278d168b339352f98_e4e255ce2420e9f88881cf7c02d3ac88_b0338240cd64a3da4abf847109e7d745.jpg",
    "type" : "image/jpeg",
    "bitrate" : 0,
    "duration" : 0,
    "title" : null,
    "properties" : null,
    "alternate" : [ {
      "href" : "https://img.abctruyen.xyz/uploads/19436/chuong-6/49.jpg",
      "type" : "image/jpeg",
      "bitrate" : 0,
      "duration" : 0,
      "title" : null,
      "properties" : null,
      "alternate" : null
    }, {
      "href" : "https://i2.wp.com/img.abctruyen.xyz/uploads/19436/chuong-6/49.jpg",
      "type" : "image/jpeg",
      "bitrate" : 0,
      "duration" : 0,
      "title" : null,
      "properties" : null,
      "alternate" : null
    } ]
  }, {
    "href" : "https://raw.githubusercontent.com/tracuumasothue40/comic_storage_two1/main/IMAGE/IMAGE_e249c88b7aab7d1278d168b339352f98_e4e255ce2420e9f88881cf7c02d3ac88_8c17e60f12e636485207dc494641a6af.jpg",
    "type" : "image/jpeg",
    "bitrate" : 0,
    "duration" : 0,
    "title" : null,
    "properties" : null,
    "alternate" : [ {
      "href" : "https://img.abctruyen.xyz/uploads/19436/chuong-6/50.jpg",
      "type" : "image/jpeg",
      "bitrate" : 0,
      "duration" : 0,
      "title" : null,
      "properties" : null,
      "alternate" : null
    }, {
      "href" : "https://i2.wp.com/img.abctruyen.xyz/uploads/19436/chuong-6/50.jpg",
      "type" : "image/jpeg",
      "bitrate" : 0,
      "duration" : 0,
      "title" : null,
      "properties" : null,
      "alternate" : null
    } ]
  }, {
    "href" : "https://raw.githubusercontent.com/tracuumasothue40/comic_storage_two1/main/IMAGE/IMAGE_e249c88b7aab7d1278d168b339352f98_e4e255ce2420e9f88881cf7c02d3ac88_8028f932cee5ab85003b15ea0132c8bc.jpg",
    "type" : "image/jpeg",
    "bitrate" : 0,
    "duration" : 0,
    "title" : null,
    "properties" : null,
    "alternate" : [ {
      "href" : "https://img.abctruyen.xyz/uploads/19436/chuong-6/51.jpg",
      "type" : "image/jpeg",
      "bitrate" : 0,
      "duration" : 0,
      "title" : null,
      "properties" : null,
      "alternate" : null
    }, {
      "href" : "https://i2.wp.com/img.abctruyen.xyz/uploads/19436/chuong-6/51.jpg",
      "type" : "image/jpeg",
      "bitrate" : 0,
      "duration" : 0,
      "title" : null,
      "properties" : null,
      "alternate" : null
    } ]
  }, {
    "href" : "https://raw.githubusercontent.com/tracuumasothue40/comic_storage_two1/main/IMAGE/IMAGE_e249c88b7aab7d1278d168b339352f98_e4e255ce2420e9f88881cf7c02d3ac88_3e380a5ac2d5f5a535e2c63cfa1e140d.jpg",
    "type" : "image/jpeg",
    "bitrate" : 0,
    "duration" : 0,
    "title" : null,
    "properties" : null,
    "alternate" : [ {
      "href" : "https://img.abctruyen.xyz/uploads/19436/chuong-6/52.jpg",
      "type" : "image/jpeg",
      "bitrate" : 0,
      "duration" : 0,
      "title" : null,
      "properties" : null,
      "alternate" : null
    }, {
      "href" : "https://i2.wp.com/img.abctruyen.xyz/uploads/19436/chuong-6/52.jpg",
      "type" : "image/jpeg",
      "bitrate" : 0,
      "duration" : 0,
      "title" : null,
      "properties" : null,
      "alternate" : null
    } ]
  }, {
    "href" : "https://raw.githubusercontent.com/tracuumasothue40/comic_storage_two1/main/IMAGE/IMAGE_e249c88b7aab7d1278d168b339352f98_e4e255ce2420e9f88881cf7c02d3ac88_b6785bb47039b31d07c7bc2c34eebcf3.jpg",
    "type" : "image/jpeg",
    "bitrate" : 0,
    "duration" : 0,
    "title" : null,
    "properties" : null,
    "alternate" : [ {
      "href" : "https://img.abctruyen.xyz/uploads/19436/chuong-6/53.jpg",
      "type" : "image/jpeg",
      "bitrate" : 0,
      "duration" : 0,
      "title" : null,
      "properties" : null,
      "alternate" : null
    }, {
      "href" : "https://i2.wp.com/img.abctruyen.xyz/uploads/19436/chuong-6/53.jpg",
      "type" : "image/jpeg",
      "bitrate" : 0,
      "duration" : 0,
      "title" : null,
      "properties" : null,
      "alternate" : null
    } ]
  }, {
    "href" : "https://raw.githubusercontent.com/tracuumasothue40/comic_storage_two1/main/IMAGE/IMAGE_e249c88b7aab7d1278d168b339352f98_e4e255ce2420e9f88881cf7c02d3ac88_eee3d87bc9d76aaf08de1db8f745fc3b.jpg",
    "type" : "image/jpeg",
    "bitrate" : 0,
    "duration" : 0,
    "title" : null,
    "properties" : null,
    "alternate" : [ {
      "href" : "https://img.abctruyen.xyz/uploads/19436/chuong-6/54.jpg",
      "type" : "image/jpeg",
      "bitrate" : 0,
      "duration" : 0,
      "title" : null,
      "properties" : null,
      "alternate" : null
    }, {
      "href" : "https://i2.wp.com/img.abctruyen.xyz/uploads/19436/chuong-6/54.jpg",
      "type" : "image/jpeg",
      "bitrate" : 0,
      "duration" : 0,
      "title" : null,
      "properties" : null,
      "alternate" : null
    } ]
  }, {
    "href" : "https://raw.githubusercontent.com/tracuumasothue40/comic_storage_two1/main/IMAGE/IMAGE_e249c88b7aab7d1278d168b339352f98_e4e255ce2420e9f88881cf7c02d3ac88_12fb4269d306900b7d7fdcc78d8cb6d3.jpg",
    "type" : "image/jpeg",
    "bitrate" : 0,
    "duration" : 0,
    "title" : null,
    "properties" : null,
    "alternate" : [ {
      "href" : "https://img.abctruyen.xyz/uploads/19436/chuong-6/55.jpg",
      "type" : "image/jpeg",
      "bitrate" : 0,
      "duration" : 0,
      "title" : null,
      "properties" : null,
      "alternate" : null
    }, {
      "href" : "https://i2.wp.com/img.abctruyen.xyz/uploads/19436/chuong-6/55.jpg",
      "type" : "image/jpeg",
      "bitrate" : 0,
      "duration" : 0,
      "title" : null,
      "properties" : null,
      "alternate" : null
    } ]
  }, {
    "href" : "https://raw.githubusercontent.com/tracuumasothue40/comic_storage_two1/main/IMAGE/IMAGE_e249c88b7aab7d1278d168b339352f98_e4e255ce2420e9f88881cf7c02d3ac88_09a0b06c56faeb170bb515c921ca96cf.jpg",
    "type" : "image/jpeg",
    "bitrate" : 0,
    "duration" : 0,
    "title" : null,
    "properties" : null,
    "alternate" : [ {
      "href" : "https://img.abctruyen.xyz/uploads/19436/chuong-6/56.jpg",
      "type" : "image/jpeg",
      "bitrate" : 0,
      "duration" : 0,
      "title" : null,
      "properties" : null,
      "alternate" : null
    }, {
      "href" : "https://i2.wp.com/img.abctruyen.xyz/uploads/19436/chuong-6/56.jpg",
      "type" : "image/jpeg",
      "bitrate" : 0,
      "duration" : 0,
      "title" : null,
      "properties" : null,
      "alternate" : null
    } ]
  }, {
    "href" : "https://raw.githubusercontent.com/tracuumasothue40/comic_storage_two1/main/IMAGE/IMAGE_e249c88b7aab7d1278d168b339352f98_e4e255ce2420e9f88881cf7c02d3ac88_1057fcd922f67805a5dae0bea46138bd.jpg",
    "type" : "image/jpeg",
    "bitrate" : 0,
    "duration" : 0,
    "title" : null,
    "properties" : null,
    "alternate" : [ {
      "href" : "https://img.abctruyen.xyz/uploads/19436/chuong-6/57.jpg",
      "type" : "image/jpeg",
      "bitrate" : 0,
      "duration" : 0,
      "title" : null,
      "properties" : null,
      "alternate" : null
    }, {
      "href" : "https://i2.wp.com/img.abctruyen.xyz/uploads/19436/chuong-6/57.jpg",
      "type" : "image/jpeg",
      "bitrate" : 0,
      "duration" : 0,
      "title" : null,
      "properties" : null,
      "alternate" : null
    } ]
  }, {
    "href" : "https://raw.githubusercontent.com/tracuumasothue40/comic_storage_two1/main/IMAGE/IMAGE_e249c88b7aab7d1278d168b339352f98_e4e255ce2420e9f88881cf7c02d3ac88_ecc979cb1a3b57e0f7f4ab6b3e3cf888.jpg",
    "type" : "image/jpeg",
    "bitrate" : 0,
    "duration" : 0,
    "title" : null,
    "properties" : null,
    "alternate" : [ {
      "href" : "https://img.abctruyen.xyz/uploads/19436/chuong-6/58.jpg",
      "type" : "image/jpeg",
      "bitrate" : 0,
      "duration" : 0,
      "title" : null,
      "properties" : null,
      "alternate" : null
    }, {
      "href" : "https://i2.wp.com/img.abctruyen.xyz/uploads/19436/chuong-6/58.jpg",
      "type" : "image/jpeg",
      "bitrate" : 0,
      "duration" : 0,
      "title" : null,
      "properties" : null,
      "alternate" : null
    } ]
  }, {
    "href" : "https://raw.githubusercontent.com/tracuumasothue40/comic_storage_two1/main/IMAGE/IMAGE_e249c88b7aab7d1278d168b339352f98_e4e255ce2420e9f88881cf7c02d3ac88_c262aad3c913d49db7d8db219490e554.jpg",
    "type" : "image/jpeg",
    "bitrate" : 0,
    "duration" : 0,
    "title" : null,
    "properties" : null,
    "alternate" : [ {
      "href" : "https://img.abctruyen.xyz/uploads/19436/chuong-6/59.jpg",
      "type" : "image/jpeg",
      "bitrate" : 0,
      "duration" : 0,
      "title" : null,
      "properties" : null,
      "alternate" : null
    }, {
      "href" : "https://i2.wp.com/img.abctruyen.xyz/uploads/19436/chuong-6/59.jpg",
      "type" : "image/jpeg",
      "bitrate" : 0,
      "duration" : 0,
      "title" : null,
      "properties" : null,
      "alternate" : null
    } ]
  }, {
    "href" : "https://raw.githubusercontent.com/tracuumasothue40/comic_storage_two1/main/IMAGE/IMAGE_e249c88b7aab7d1278d168b339352f98_e4e255ce2420e9f88881cf7c02d3ac88_4e55ec07cec6791f438d81b857394b5e.jpg",
    "type" : "image/jpeg",
    "bitrate" : 0,
    "duration" : 0,
    "title" : null,
    "properties" : null,
    "alternate" : [ {
      "href" : "https://img.abctruyen.xyz/uploads/19436/chuong-6/60.jpg",
      "type" : "image/jpeg",
      "bitrate" : 0,
      "duration" : 0,
      "title" : null,
      "properties" : null,
      "alternate" : null
    }, {
      "href" : "https://i2.wp.com/img.abctruyen.xyz/uploads/19436/chuong-6/60.jpg",
      "type" : "image/jpeg",
      "bitrate" : 0,
      "duration" : 0,
      "title" : null,
      "properties" : null,
      "alternate" : null
    } ]
  }, {
    "href" : "https://raw.githubusercontent.com/tracuumasothue40/comic_storage_two1/main/IMAGE/IMAGE_e249c88b7aab7d1278d168b339352f98_e4e255ce2420e9f88881cf7c02d3ac88_ed6dffd659cd1102e7e07eefd0462b0b.jpg",
    "type" : "image/jpeg",
    "bitrate" : 0,
    "duration" : 0,
    "title" : null,
    "properties" : null,
    "alternate" : [ {
      "href" : "https://img.abctruyen.xyz/uploads/19436/chuong-6/61.jpg",
      "type" : "image/jpeg",
      "bitrate" : 0,
      "duration" : 0,
      "title" : null,
      "properties" : null,
      "alternate" : null
    }, {
      "href" : "https://i2.wp.com/img.abctruyen.xyz/uploads/19436/chuong-6/61.jpg",
      "type" : "image/jpeg",
      "bitrate" : 0,
      "duration" : 0,
      "title" : null,
      "properties" : null,
      "alternate" : null
    } ]
  } ],
  "toc" : null,
  "@context" : "https://readium.org/webpub-manifest/context.jsonld"
}